micropython_vcnl4010/__init__.py
micropython_vcnl4010/i2c_helpers.py
micropython_vcnl4010/vcnl4010.py
micropython_vcnl4010-0.1.0.dist-info/LICENSE
micropython_vcnl4010-0.1.0.dist-info/METADATA
micropython_vcnl4010-0.1.0.dist-info/WHEEL
micropython_vcnl4010-0.1.0.dist-info/top_level.txt
micropython_vcnl4010-0.1.0.dist-info/RECORD
