Metadata-Version: 2.1
Name: micropython-vcnl4010
Version: 0.1.0
Summary: MicroPython Driver for the Vishay VCNL4010 Proximity and Ambient Light Sensor
Author-email: JDM <xxyx@mailmeto.mozmail.com>
License: MIT
Project-URL: Homepage, https://github.com/jposada202020/MicroPython_VCNL4010
Keywords: sensor,micropython,vcnl4010,light,micropython,vishay,vcnl4010,proximity,driver,sensor
Classifier: Intended Audience :: Developers
Classifier: Topic :: Software Development :: Libraries
Classifier: Topic :: Software Development :: Embedded Systems
Classifier: Topic :: System :: Hardware
Classifier: License :: OSI Approved :: MIT License
Classifier: Programming Language :: Python :: Implementation :: MicroPython
License-File: LICENSE
